fancy_tree/cli.py
fancy_tree/main.py
fancy_tree/schema.py
fancy_tree/config/__init__.py
fancy_tree/config/languages.yaml
fancy_tree/core/__init__.py
fancy_tree/core/config.py
fancy_tree/core/discovery.py
fancy_tree/core/extraction.py
fancy_tree/core/formatter.py
fancy_tree/extractors/__init__.py
fancy_tree/extractors/base.py
fancy_tree/extractors/c.py
fancy_tree/extractors/cpp.py
fancy_tree/extractors/csharp.py
fancy_tree/extractors/go.py
fancy_tree/extractors/java.py
fancy_tree/extractors/javascript.py
fancy_tree/extractors/php.py
fancy_tree/extractors/python.py
fancy_tree/extractors/ruby.py
fancy_tree/extractors/rust.py
fancy_tree/extractors/typescript.py
fancy_tree-0.1.9.dist-info/METADATA
fancy_tree-0.1.9.dist-info/WHEEL
fancy_tree-0.1.9.dist-info/entry_points.txt
fancy_tree-0.1.9.dist-info/top_level.txt
fancy_tree-0.1.9.dist-info/RECORD
